pydynet/__init__.py
pydynet/autograd.py
pydynet/cuda.py
pydynet/data.py
pydynet/special.py
pydynet/core/__init__.py
pydynet/core/function.py
pydynet/core/tensor.py
pydynet/nn/__init__.py
pydynet/nn/functional.py
pydynet/nn/init.py
pydynet/nn/parameter.py
pydynet/nn/modules/__init__.py
pydynet/nn/modules/activation.py
pydynet/nn/modules/conv.py
pydynet/nn/modules/dropout.py
pydynet/nn/modules/linear.py
pydynet/nn/modules/loss.py
pydynet/nn/modules/module.py
pydynet/nn/modules/norm.py
pydynet/nn/modules/pool.py
pydynet/nn/modules/rnn.py
pydynet/optim/__init__.py
pydynet/optim/lr_scheduler.py
pydynet/optim/optimizer.py
pydynet-1.0.dist-info/licenses/LICENSE
pydynet-1.0.dist-info/METADATA
pydynet-1.0.dist-info/WHEEL
pydynet-1.0.dist-info/top_level.txt
pydynet-1.0.dist-info/RECORD
