Metadata-Version: 2.4
Name: pydynet
Version: 1.0
Summary: PyDyNet: Neuron Network (MLP, CNN, RNN, Transformer, ...) implementation using Numpy with Autodiff
Home-page: https://github.com/WeltXing/PyDyNet
Author: Cun-Yuan Xing
Author-email: xingcy@lamda.nju.edu.cn
Maintainer: Cun-Yuan Xing
Maintainer-email: xingcy@lamad.nju.edu.cn
License: MIT License
License-File: LICENSE
Requires-Dist: numpy>=2.0.0
Dynamic: author
Dynamic: author-email
Dynamic: description
Dynamic: description-content-type
Dynamic: home-page
Dynamic: license
Dynamic: license-file
Dynamic: maintainer
Dynamic: maintainer-email
Dynamic: requires-dist
Dynamic: summary
